HighchartsZhongwenJiaocheng/README.md
HighchartsZhongwenJiaocheng/__init__.py
HighchartsZhongwenJiaocheng/__main__.py
HighchartsZhongwenJiaocheng/file.epub
HighchartsZhongwenJiaocheng/index.html
HighchartsZhongwenJiaocheng/css/__init__.py
HighchartsZhongwenJiaocheng/css/annotations.css
HighchartsZhongwenJiaocheng/css/main.css
HighchartsZhongwenJiaocheng/css/normalize.css
HighchartsZhongwenJiaocheng/css/popup.css
HighchartsZhongwenJiaocheng/font/__init__.py
HighchartsZhongwenJiaocheng/font/fontello.eot
HighchartsZhongwenJiaocheng/font/fontello.svg
HighchartsZhongwenJiaocheng/font/fontello.ttf
HighchartsZhongwenJiaocheng/font/fontello.woff
HighchartsZhongwenJiaocheng/img/__init__.py
HighchartsZhongwenJiaocheng/img/annotator-glyph-sprite.png
HighchartsZhongwenJiaocheng/img/annotator-icon-sprite.png
HighchartsZhongwenJiaocheng/img/apple-touch-icon.png
HighchartsZhongwenJiaocheng/img/cancelfullscreen.png
HighchartsZhongwenJiaocheng/img/close.png
HighchartsZhongwenJiaocheng/img/fullscreen.png
HighchartsZhongwenJiaocheng/img/loader.gif
HighchartsZhongwenJiaocheng/img/menu-icon.png
HighchartsZhongwenJiaocheng/img/save.png
HighchartsZhongwenJiaocheng/img/saved.png
HighchartsZhongwenJiaocheng/img/settings-s.png
HighchartsZhongwenJiaocheng/img/settings.png
HighchartsZhongwenJiaocheng/img/star.png
HighchartsZhongwenJiaocheng/js/__init__.py
HighchartsZhongwenJiaocheng/js/epub.js
HighchartsZhongwenJiaocheng/js/epub.min.js
HighchartsZhongwenJiaocheng/js/epub.min.map
HighchartsZhongwenJiaocheng/js/hooks.min.js
HighchartsZhongwenJiaocheng/js/hooks.min.map
HighchartsZhongwenJiaocheng/js/reader.js
HighchartsZhongwenJiaocheng/js/reader.js.map
HighchartsZhongwenJiaocheng/js/reader.min.js
HighchartsZhongwenJiaocheng/js/reader.min.map
HighchartsZhongwenJiaocheng/js/hooks/__init__.py
HighchartsZhongwenJiaocheng/js/hooks/extensions/__init__.py
HighchartsZhongwenJiaocheng/js/hooks/extensions/highlight.js
HighchartsZhongwenJiaocheng/js/libs/__init__.py
highcharts_zhongwen_jiaocheng-2024.3.2.0.dist-info/METADATA
highcharts_zhongwen_jiaocheng-2024.3.2.0.dist-info/WHEEL
highcharts_zhongwen_jiaocheng-2024.3.2.0.dist-info/entry_points.txt
highcharts_zhongwen_jiaocheng-2024.3.2.0.dist-info/top_level.txt
highcharts_zhongwen_jiaocheng-2024.3.2.0.dist-info/RECORD
